adtoolbox/.DS_Store
adtoolbox/__init__.py
adtoolbox/__main__.py
adtoolbox/adm.py
adtoolbox/bio_struct.py
adtoolbox/cli.py
adtoolbox/configs.py
adtoolbox/core.py
adtoolbox/metagenomics_report.py
adtoolbox/optimize.py
adtoolbox/pipeline.py
adtoolbox/pkg_data/.DS_Store
adtoolbox/pkg_data/Modified_ADM_Map.json
adtoolbox/pkg_data/Modified_ADM_Model.json
adtoolbox/pkg_data/README.md
adtoolbox/pkg_data/qiime_template_paired.txt
adtoolbox/pkg_data/qiime_template_single.txt
adtoolbox/pkg_data/slurm_template.txt
adtoolbox/stats.py
adtoolbox/tables.py
adtoolbox/utils.py
adtoolbox-0.6.18.dist-info/entry_points.txt
adtoolbox-0.6.18.dist-info/WHEEL
adtoolbox-0.6.18.dist-info/METADATA
adtoolbox-0.6.18.dist-info/RECORD
