Metadata-Version: 2.1
Name: adtoolbox
Version: 0.6.18
Summary: A tool for modeling and optimization of anaerobic digestion process.
Author: ParsaGhadermazi
Author-email: 54489047+ParsaGhadermazi@users.noreply.github.com
Requires-Python: >=3.9,<3.13
Classifier: Programming Language :: Python :: 3
Classifier: Programming Language :: Python :: 3.10
Classifier: Programming Language :: Python :: 3.9
Provides-Extra: optimize
Requires-Dist: dash (>=2.4.1,<3.0.0)
Requires-Dist: dash-bootstrap-components (>=1.3.1,<2.0.0)
Requires-Dist: dash-escher (>=0.0.4,<0.0.5)
Requires-Dist: matplotlib (>=3.5.2,<4.0.0)
Requires-Dist: numpy (>=1.22.4,<2.0.0)
Requires-Dist: pandas (>=1.4.2,<2.0.0)
Requires-Dist: plotly (>=5.8.0,<6.0.0)
Requires-Dist: polars (>=0.20.27,<0.21.0)
Requires-Dist: ray (>=2.37.0,<3.0.0); extra == "optimize"
Requires-Dist: requests (>=2.27.1,<3.0.0)
Requires-Dist: rich (>=12.4.4,<13.0.0)
Requires-Dist: scipy (>=1.8.1,<2.0.0)
Requires-Dist: sympy (>=1.10.1,<2.0.0)
Requires-Dist: torch (>=2.4.1,<3.0.0); extra == "optimize"
